easy_lightning/__init__.py
easy_lightning/cli.py
easy_lightning/cfg/easy_rec_cfg/config_rec.yaml
easy_lightning/cfg/easy_rec_cfg/data_params/data_cfg.yaml
easy_lightning/cfg/easy_rec_cfg/model/model.yaml
easy_lightning/cfg/easy_rec_cfg/model/loader_params/loader_params_cfg.yaml
easy_lightning/cfg/easy_rec_cfg/model/rec_model/BERT4Rec.yaml
easy_lightning/cfg/easy_rec_cfg/model/rec_model/CORE.yaml
easy_lightning/cfg/easy_rec_cfg/model/rec_model/Caser.yaml
easy_lightning/cfg/easy_rec_cfg/model/rec_model/Caser2.yaml
easy_lightning/cfg/easy_rec_cfg/model/rec_model/CosRec.yaml
easy_lightning/cfg/easy_rec_cfg/model/rec_model/CosRec2.yaml
easy_lightning/cfg/easy_rec_cfg/model/rec_model/GRU4Rec.yaml
easy_lightning/cfg/easy_rec_cfg/model/rec_model/GRU4Rec_OLD.yaml
easy_lightning/cfg/easy_rec_cfg/model/rec_model/HGN.yaml
easy_lightning/cfg/easy_rec_cfg/model/rec_model/LightGCN.yaml
easy_lightning/cfg/easy_rec_cfg/model/rec_model/Mamba4Rec.yaml
easy_lightning/cfg/easy_rec_cfg/model/rec_model/NARM.yaml
easy_lightning/cfg/easy_rec_cfg/model/rec_model/NCF.yaml
easy_lightning/cfg/easy_rec_cfg/model/rec_model/SASRec.yaml
easy_lightning/cfg/easy_rec_cfg/model/trainer_params/trainer_params_cfg.yaml
easy_lightning/cfg/easy_torch_cfg/config_nn.yaml
easy_lightning/cfg/easy_torch_cfg/data_params/data_cfg.yaml
easy_lightning/cfg/easy_torch_cfg/model/model.yaml
easy_lightning/cfg/easy_torch_cfg/model/loader_params/loader_params_cfg.yaml
easy_lightning/cfg/easy_torch_cfg/model/torch_model/nn.yaml
easy_lightning/cfg/easy_torch_cfg/model/torch_model/resnet18.yaml
easy_lightning/cfg/easy_torch_cfg/model/trainer_params/trainer_params_cfg.yaml
easy_lightning/easy_data/__init__.py
easy_lightning/easy_data/_version.py
easy_lightning/easy_data/data.py
easy_lightning/easy_data/file.py
easy_lightning/easy_data/stat.py
easy_lightning/easy_data/stats.py
easy_lightning/easy_data/torch.py
easy_lightning/easy_data/transform.py
easy_lightning/easy_data/uci.py
easy_lightning/easy_data/utils.py
easy_lightning-1.0.4.dist-info/licenses/LICENSE
easy_lightning-1.0.4.dist-info/METADATA
easy_lightning-1.0.4.dist-info/WHEEL
easy_lightning-1.0.4.dist-info/entry_points.txt
easy_lightning-1.0.4.dist-info/top_level.txt
easy_lightning-1.0.4.dist-info/RECORD
