Metadata-Version: 2.4
Name: easy_lightning
Version: 1.0.4
Summary: Easy Lightning: Simplify AI-Deep learning with PyTorch Lightning
Author-email: Filippo Betello <betello@diag.uniroma1.it>, Maria Diana Calagaru <calagaru@diag.uniroma1.it>, Erica Luciani <luciani@diag.uniroma1.it>, Antonio Purificato <purificato@diag.uniroma1.it>, Federico Siciliano <siciliano@diag.uniroma1.it>
License: MIT
Project-URL: Homepage, https://github.com/federicosiciliano/easy_lightning
Project-URL: Issues, https://github.com/federicosiciliano/easy_lightning/issues
Classifier: Programming Language :: Python :: 3
Classifier: Operating System :: OS Independent
Requires-Python: >=3.9.20
License-File: LICENSE
Requires-Dist: attr>=0.3.2
Requires-Dist: codecarbon>=3.0.4
Requires-Dist: colorama>=0.4.6
Requires-Dist: ConfigParser>=7.2.0
Requires-Dist: deepspeed>=0.17.2
Requires-Dist: HTMLParser>=0.0.2
Requires-Dist: imageio>=2.37.0
Requires-Dist: matplotlib>=3.9.0
Requires-Dist: protobuf>=6.31.1
Requires-Dist: pyOpenSSL>=25.1.0
Requires-Dist: pytorch_lightning>=2.5.2
Requires-Dist: ray==2.40.0
Requires-Dist: redis>=6.2.0
Requires-Dist: scikit_learn>=1.6.0
Requires-Dist: Sphinx>=7.4.0
Requires-Dist: thread>=2.0.5
Requires-Dist: torchvision>=0.22.1
Requires-Dist: pyarrow>=21.0.0
Requires-Dist: wandb>=0.21.0
Dynamic: license-file
